LICENSE
README.md
setup.py
InstaTweet/__init__.py
InstaTweet/utils.py
InstaTweet/core/__init__.py
InstaTweet/core/instaclient.py
InstaTweet/core/instapost.py
InstaTweet/core/instatweet.py
InstaTweet/core/instauser.py
InstaTweet/core/tweetclient.py
InstaTweet/core/__init__.py
InstaTweet/core/instaclient.py
InstaTweet/core/instapost.py
InstaTweet/core/instatweet.py
InstaTweet/core/instauser.py
InstaTweet/core/tweetclient.py
insta_tweet.egg-info/PKG-INFO
insta_tweet.egg-info/SOURCES.txt
insta_tweet.egg-info/dependency_links.txt
insta_tweet.egg-info/requires.txt
insta_tweet.egg-info/top_level.txt