Metadata-Version: 2.1
Name: insta-tweet
Version: 1.1.1
Summary: Automatically Repost Content From Instagram to Twitter
Home-page: https://www.github.com/TDKorn/insta-tweet
Author: Adam Korn
Author-email: hello@dailykitten.net
License: MIT
Download-URL: https://github.com/TDKorn/insta-tweet/tarball/master
Keywords: instagram,twitter,repost,reposter,instascrape,instagram-repost
Platform: UNKNOWN
License-File: LICENSE
